{
 "@context": "http://iiif.io/api/presentation/3/context.json",
 "id": "iiif/annotations/A16098000544-objects.json",
 "type": "AnnotationPage",
 "items": [
  {
   "@context": "http://iiif.io/api/presentation/3/context.json",
   "id": "https://data.goldenagents.org/datasets/fricktalk2023/annotation/A16098000544/object1",
   "type": "Annotation",
   "motivation": "commenting",
   "body": [
    {
     "type": "TextualBody",
     "language": "nl",
     "value": "<p><b>Object detection</b><br><span>Original Label: </span>twee slooten<br>\n<span>Modernized Label: </span>twee sloten</p>"
    },
    {
     "type": "TextualBody",
     "purpose": "tagging",
     "value": "Object"
    }
   ],
   "target": {
    "id": "https://data.goldenagents.org/datasets/fricktalk2023/canvas/A16098000544",
    "selector": {
     "type": "FragmentSelector",
     "value": "xywh=664,258,1411,175"
    }
   }
  },
  {
   "@context": "http://iiif.io/api/presentation/3/context.json",
   "id": "https://data.goldenagents.org/datasets/fricktalk2023/annotation/A16098000544/object2",
   "type": "Annotation",
   "motivation": "commenting",
   "body": [
    {
     "type": "TextualBody",
     "language": "nl",
     "value": "<p><b>Object detection</b><br><span>Original Label: </span>Een beslaagen ijser kisje<br>\n<span>Modernized Label: </span>een beslagen ijzer kistje</p>"
    },
    {
     "type": "TextualBody",
     "purpose": "tagging",
     "value": "Object"
    }
   ],
   "target": {
    "id": "https://data.goldenagents.org/datasets/fricktalk2023/canvas/A16098000544",
    "selector": {
     "type": "FragmentSelector",
     "value": "xywh=664,258,1411,175"
    }
   }
  },
  {
   "@context": "http://iiif.io/api/presentation/3/context.json",
   "id": "https://data.goldenagents.org/datasets/fricktalk2023/annotation/A16098000544/object3",
   "type": "Annotation",
   "motivation": "commenting",
   "body": [
    {
     "type": "TextualBody",
     "language": "nl",
     "value": "<p><b>Object detection</b><br><span>Original Label: </span>Een ijsere kist<br>\n<span>Modernized Label: </span>een ijzer kist</p>"
    },
    {
     "type": "TextualBody",
     "purpose": "tagging",
     "value": "Object"
    }
   ],
   "target": {
    "id": "https://data.goldenagents.org/datasets/fricktalk2023/canvas/A16098000544",
    "selector": {
     "type": "FragmentSelector",
     "value": "xywh=308,374,462,131"
    }
   }
  },
  {
   "@context": "http://iiif.io/api/presentation/3/context.json",
   "id": "https://data.goldenagents.org/datasets/fricktalk2023/annotation/A16098000544/object4",
   "type": "Annotation",
   "motivation": "commenting",
   "body": [
    {
     "type": "TextualBody",
     "language": "nl",
     "value": "<p><b>Object detection</b><br><span>Original Label: </span>Een groot boeck<br>\n<span>Modernized Label: </span>een groot boek</p>"
    },
    {
     "type": "TextualBody",
     "purpose": "tagging",
     "value": "Object"
    }
   ],
   "target": {
    "id": "https://data.goldenagents.org/datasets/fricktalk2023/canvas/A16098000544",
    "selector": {
     "type": "FragmentSelector",
     "value": "xywh=873,602,1650,139"
    }
   }
  },
  {
   "@context": "http://iiif.io/api/presentation/3/context.json",
   "id": "https://data.goldenagents.org/datasets/fricktalk2023/annotation/A16098000544/object5",
   "type": "Annotation",
   "motivation": "commenting",
   "body": [
    {
     "type": "TextualBody",
     "language": "nl",
     "value": "<p><b>Object detection</b><br><span>Original Label: </span>Een silvere kan<br>\n<span>Modernized Label: </span>een zilver kan</p>"
    },
    {
     "type": "TextualBody",
     "purpose": "tagging",
     "value": "Object"
    }
   ],
   "target": {
    "id": "https://data.goldenagents.org/datasets/fricktalk2023/canvas/A16098000544",
    "selector": {
     "type": "FragmentSelector",
     "value": "xywh=313,818,693,104"
    }
   }
  },
  {
   "@context": "http://iiif.io/api/presentation/3/context.json",
   "id": "https://data.goldenagents.org/datasets/fricktalk2023/annotation/A16098000544/object6",
   "type": "Annotation",
   "motivation": "commenting",
   "body": [
    {
     "type": "TextualBody",
     "language": "nl",
     "value": "<p><b>Object detection</b><br><span>Original Label: </span>een pijp<br>\n<span>Modernized Label: </span>een pijp</p>"
    },
    {
     "type": "TextualBody",
     "purpose": "tagging",
     "value": "Object"
    }
   ],
   "target": {
    "id": "https://data.goldenagents.org/datasets/fricktalk2023/canvas/A16098000544",
    "selector": {
     "type": "FragmentSelector",
     "value": "xywh=313,818,693,104"
    }
   }
  },
  {
   "@context": "http://iiif.io/api/presentation/3/context.json",
   "id": "https://data.goldenagents.org/datasets/fricktalk2023/annotation/A16098000544/object7",
   "type": "Annotation",
   "motivation": "commenting",
   "body": [
    {
     "type": "TextualBody",
     "language": "nl",
     "value": "<p><b>Object detection</b><br><span>Original Label: </span>Een ditto wat<br>\n<span>Modernized Label: </span>een dito wat</p>"
    },
    {
     "type": "TextualBody",
     "purpose": "tagging",
     "value": "Object"
    }
   ],
   "target": {
    "id": "https://data.goldenagents.org/datasets/fricktalk2023/canvas/A16098000544",
    "selector": {
     "type": "FragmentSelector",
     "value": "xywh=311,884,530,95"
    }
   }
  },
  {
   "@context": "http://iiif.io/api/presentation/3/context.json",
   "id": "https://data.goldenagents.org/datasets/fricktalk2023/annotation/A16098000544/object8",
   "type": "Annotation",
   "motivation": "commenting",
   "body": [
    {
     "type": "TextualBody",
     "language": "nl",
     "value": "<p><b>Object detection</b><br><span>Original Label: </span>Vier silvere Soutvaten<br>\n<span>Modernized Label: </span>vier zilver zoutvat</p>"
    },
    {
     "type": "TextualBody",
     "purpose": "tagging",
     "value": "Object"
    }
   ],
   "target": {
    "id": "https://data.goldenagents.org/datasets/fricktalk2023/canvas/A16098000544",
    "selector": {
     "type": "FragmentSelector",
     "value": "xywh=305,1012,550,99"
    }
   }
  },
  {
   "@context": "http://iiif.io/api/presentation/3/context.json",
   "id": "https://data.goldenagents.org/datasets/fricktalk2023/annotation/A16098000544/object9",
   "type": "Annotation",
   "motivation": "commenting",
   "body": [
    {
     "type": "TextualBody",
     "language": "nl",
     "value": "<p><b>Object detection</b><br><span>Original Label: </span>een groot boeck<br>\n<span>Modernized Label: </span>een groot boek</p>"
    },
    {
     "type": "TextualBody",
     "purpose": "tagging",
     "value": "Object"
    }
   ],
   "target": {
    "id": "https://data.goldenagents.org/datasets/fricktalk2023/canvas/A16098000544",
    "selector": {
     "type": "FragmentSelector",
     "value": "xywh=878,1070,1715,132"
    }
   }
  },
  {
   "@context": "http://iiif.io/api/presentation/3/context.json",
   "id": "https://data.goldenagents.org/datasets/fricktalk2023/annotation/A16098000544/object10",
   "type": "Annotation",
   "motivation": "commenting",
   "body": [
    {
     "type": "TextualBody",
     "language": "nl",
     "value": "<p><b>Object detection</b><br><span>Original Label: </span>Een silvere mosterpot<br>\n<span>Modernized Label: </span>een zilver mosterdpot</p>"
    },
    {
     "type": "TextualBody",
     "purpose": "tagging",
     "value": "Object"
    }
   ],
   "target": {
    "id": "https://data.goldenagents.org/datasets/fricktalk2023/canvas/A16098000544",
    "selector": {
     "type": "FragmentSelector",
     "value": "xywh=303,1088,553,106"
    }
   }
  },
  {
   "@context": "http://iiif.io/api/presentation/3/context.json",
   "id": "https://data.goldenagents.org/datasets/fricktalk2023/annotation/A16098000544/object11",
   "type": "Annotation",
   "motivation": "commenting",
   "body": [
    {
     "type": "TextualBody",
     "language": "nl",
     "value": "<p><b>Object detection</b><br><span>Original Label: </span>Een kroesken<br>\n<span>Modernized Label: </span>een kroes</p>"
    },
    {
     "type": "TextualBody",
     "purpose": "tagging",
     "value": "Object"
    }
   ],
   "target": {
    "id": "https://data.goldenagents.org/datasets/fricktalk2023/canvas/A16098000544",
    "selector": {
     "type": "FragmentSelector",
     "value": "xywh=309,1162,348,96"
    }
   }
  },
  {
   "@context": "http://iiif.io/api/presentation/3/context.json",
   "id": "https://data.goldenagents.org/datasets/fricktalk2023/annotation/A16098000544/object12",
   "type": "Annotation",
   "motivation": "commenting",
   "body": [
    {
     "type": "TextualBody",
     "language": "nl",
     "value": "<p><b>Object detection</b><br><span>Original Label: </span>Acht silvere lepels<br>\n<span>Modernized Label: </span>acht zilver lepels</p>"
    },
    {
     "type": "TextualBody",
     "purpose": "tagging",
     "value": "Object"
    }
   ],
   "target": {
    "id": "https://data.goldenagents.org/datasets/fricktalk2023/canvas/A16098000544",
    "selector": {
     "type": "FragmentSelector",
     "value": "xywh=286,1183,465,138"
    }
   }
  },
  {
   "@context": "http://iiif.io/api/presentation/3/context.json",
   "id": "https://data.goldenagents.org/datasets/fricktalk2023/annotation/A16098000544/object13",
   "type": "Annotation",
   "motivation": "commenting",
   "body": [
    {
     "type": "TextualBody",
     "language": "nl",
     "value": "<p><b>Object detection</b><br><span>Original Label: </span>Een ditto eijerlepeltje<br>\n<span>Modernized Label: </span>een dito eierlepeltje</p>"
    },
    {
     "type": "TextualBody",
     "purpose": "tagging",
     "value": "Object"
    }
   ],
   "target": {
    "id": "https://data.goldenagents.org/datasets/fricktalk2023/canvas/A16098000544",
    "selector": {
     "type": "FragmentSelector",
     "value": "xywh=289,1297,493,94"
    }
   }
  },
  {
   "@context": "http://iiif.io/api/presentation/3/context.json",
   "id": "https://data.goldenagents.org/datasets/fricktalk2023/annotation/A16098000544/object14",
   "type": "Annotation",
   "motivation": "commenting",
   "body": [
    {
     "type": "TextualBody",
     "language": "nl",
     "value": "<p><b>Object detection</b><br><span>Original Label: </span>Acht silvere vorckjens<br>\n<span>Modernized Label: </span>acht zilver vorkje</p>"
    },
    {
     "type": "TextualBody",
     "purpose": "tagging",
     "value": "Object"
    }
   ],
   "target": {
    "id": "https://data.goldenagents.org/datasets/fricktalk2023/canvas/A16098000544",
    "selector": {
     "type": "FragmentSelector",
     "value": "xywh=301,1372,482,89"
    }
   }
  },
  {
   "@context": "http://iiif.io/api/presentation/3/context.json",
   "id": "https://data.goldenagents.org/datasets/fricktalk2023/annotation/A16098000544/object15",
   "type": "Annotation",
   "motivation": "commenting",
   "body": [
    {
     "type": "TextualBody",
     "language": "nl",
     "value": "<p><b>Object detection</b><br><span>Original Label: </span>Een Silvere onderriem<br>\n<span>Modernized Label: </span>een zilver onderriem</p>"
    },
    {
     "type": "TextualBody",
     "purpose": "tagging",
     "value": "Object"
    }
   ],
   "target": {
    "id": "https://data.goldenagents.org/datasets/fricktalk2023/canvas/A16098000544",
    "selector": {
     "type": "FragmentSelector",
     "value": "xywh=305,1430,520,95"
    }
   }
  },
  {
   "@context": "http://iiif.io/api/presentation/3/context.json",
   "id": "https://data.goldenagents.org/datasets/fricktalk2023/annotation/A16098000544/object16",
   "type": "Annotation",
   "motivation": "commenting",
   "body": [
    {
     "type": "TextualBody",
     "language": "nl",
     "value": "<p><b>Object detection</b><br><span>Original Label: </span>silvere knoopen<br>\n<span>Modernized Label: </span>zilver knoop</p>"
    },
    {
     "type": "TextualBody",
     "purpose": "tagging",
     "value": "Object"
    }
   ],
   "target": {
    "id": "https://data.goldenagents.org/datasets/fricktalk2023/canvas/A16098000544",
    "selector": {
     "type": "FragmentSelector",
     "value": "xywh=285,1499,664,105"
    }
   }
  },
  {
   "@context": "http://iiif.io/api/presentation/3/context.json",
   "id": "https://data.goldenagents.org/datasets/fricktalk2023/annotation/A16098000544/object17",
   "type": "Annotation",
   "motivation": "commenting",
   "body": [
    {
     "type": "TextualBody",
     "language": "nl",
     "value": "<p><b>Object detection</b><br><span>Original Label: </span>Een groot boeck<br>\n<span>Modernized Label: </span>een groot boek</p>"
    },
    {
     "type": "TextualBody",
     "purpose": "tagging",
     "value": "Object"
    }
   ],
   "target": {
    "id": "https://data.goldenagents.org/datasets/fricktalk2023/canvas/A16098000544",
    "selector": {
     "type": "FragmentSelector",
     "value": "xywh=872,1607,1722,123"
    }
   }
  },
  {
   "@context": "http://iiif.io/api/presentation/3/context.json",
   "id": "https://data.goldenagents.org/datasets/fricktalk2023/annotation/A16098000544/object18",
   "type": "Annotation",
   "motivation": "commenting",
   "body": [
    {
     "type": "TextualBody",
     "language": "nl",
     "value": "<p><b>Object detection</b><br><span>Original Label: </span>een kettinghje<br>\n<span>Modernized Label: </span>een kettinkje</p>"
    },
    {
     "type": "TextualBody",
     "purpose": "tagging",
     "value": "Object"
    }
   ],
   "target": {
    "id": "https://data.goldenagents.org/datasets/fricktalk2023/canvas/A16098000544",
    "selector": {
     "type": "FragmentSelector",
     "value": "xywh=333,1642,329,85"
    }
   }
  },
  {
   "@context": "http://iiif.io/api/presentation/3/context.json",
   "id": "https://data.goldenagents.org/datasets/fricktalk2023/annotation/A16098000544/object19",
   "type": "Annotation",
   "motivation": "commenting",
   "body": [
    {
     "type": "TextualBody",
     "language": "nl",
     "value": "<p><b>Object detection</b><br><span>Original Label: </span>Twee silvere kettinghjens in<br>\n<span>Modernized Label: </span>twee zilver kettinkjes</p>"
    },
    {
     "type": "TextualBody",
     "purpose": "tagging",
     "value": "Object"
    }
   ],
   "target": {
    "id": "https://data.goldenagents.org/datasets/fricktalk2023/canvas/A16098000544",
    "selector": {
     "type": "FragmentSelector",
     "value": "xywh=276,1732,625,116"
    }
   }
  },
  {
   "@context": "http://iiif.io/api/presentation/3/context.json",
   "id": "https://data.goldenagents.org/datasets/fricktalk2023/annotation/A16098000544/object20",
   "type": "Annotation",
   "motivation": "commenting",
   "body": [
    {
     "type": "TextualBody",
     "language": "nl",
     "value": "<p><b>Object detection</b><br><span>Original Label: </span>Een silver taeffelbort<br>\n<span>Modernized Label: </span>een zilver tafelbord</p>"
    },
    {
     "type": "TextualBody",
     "purpose": "tagging",
     "value": "Object"
    }
   ],
   "target": {
    "id": "https://data.goldenagents.org/datasets/fricktalk2023/canvas/A16098000544",
    "selector": {
     "type": "FragmentSelector",
     "value": "xywh=285,1859,551,117"
    }
   }
  },
  {
   "@context": "http://iiif.io/api/presentation/3/context.json",
   "id": "https://data.goldenagents.org/datasets/fricktalk2023/annotation/A16098000544/object21",
   "type": "Annotation",
   "motivation": "commenting",
   "body": [
    {
     "type": "TextualBody",
     "language": "nl",
     "value": "<p><b>Object detection</b><br><span>Original Label: </span>Een silver hooftijser<br>\n<span>Modernized Label: </span>een zilver oorijzer</p>"
    },
    {
     "type": "TextualBody",
     "purpose": "tagging",
     "value": "Object"
    }
   ],
   "target": {
    "id": "https://data.goldenagents.org/datasets/fricktalk2023/canvas/A16098000544",
    "selector": {
     "type": "FragmentSelector",
     "value": "xywh=312,1935,473,109"
    }
   }
  },
  {
   "@context": "http://iiif.io/api/presentation/3/context.json",
   "id": "https://data.goldenagents.org/datasets/fricktalk2023/annotation/A16098000544/object22",
   "type": "Annotation",
   "motivation": "commenting",
   "body": [
    {
     "type": "TextualBody",
     "language": "nl",
     "value": "<p><b>Object detection</b><br><span>Original Label: </span>twee parlen<br>\n<span>Modernized Label: </span>twee parel</p>"
    },
    {
     "type": "TextualBody",
     "purpose": "tagging",
     "value": "Object"
    }
   ],
   "target": {
    "id": "https://data.goldenagents.org/datasets/fricktalk2023/canvas/A16098000544",
    "selector": {
     "type": "FragmentSelector",
     "value": "xywh=343,1999,373,77"
    }
   }
  },
  {
   "@context": "http://iiif.io/api/presentation/3/context.json",
   "id": "https://data.goldenagents.org/datasets/fricktalk2023/annotation/A16098000544/object23",
   "type": "Annotation",
   "motivation": "commenting",
   "body": [
    {
     "type": "TextualBody",
     "language": "nl",
     "value": "<p><b>Object detection</b><br><span>Original Label: </span>Twee parlemoere messen<br>\n<span>Modernized Label: </span>twee parelmoer messen</p>"
    },
    {
     "type": "TextualBody",
     "purpose": "tagging",
     "value": "Object"
    }
   ],
   "target": {
    "id": "https://data.goldenagents.org/datasets/fricktalk2023/canvas/A16098000544",
    "selector": {
     "type": "FragmentSelector",
     "value": "xywh=279,2135,650,105"
    }
   }
  },
  {
   "@context": "http://iiif.io/api/presentation/3/context.json",
   "id": "https://data.goldenagents.org/datasets/fricktalk2023/annotation/A16098000544/object24",
   "type": "Annotation",
   "motivation": "commenting",
   "body": [
    {
     "type": "TextualBody",
     "language": "nl",
     "value": "<p><b>Object detection</b><br><span>Original Label: </span>silver vorckje<br>\n<span>Modernized Label: </span>zilver vorkje</p>"
    },
    {
     "type": "TextualBody",
     "purpose": "tagging",
     "value": "Object"
    }
   ],
   "target": {
    "id": "https://data.goldenagents.org/datasets/fricktalk2023/canvas/A16098000544",
    "selector": {
     "type": "FragmentSelector",
     "value": "xywh=323,2257,321,82"
    }
   }
  },
  {
   "@context": "http://iiif.io/api/presentation/3/context.json",
   "id": "https://data.goldenagents.org/datasets/fricktalk2023/annotation/A16098000544/object25",
   "type": "Annotation",
   "motivation": "commenting",
   "body": [
    {
     "type": "TextualBody",
     "language": "nl",
     "value": "<p><b>Object detection</b><br><span>Original Label: </span>den prino<br>\n<span>Modernized Label: </span>de prent</p>"
    },
    {
     "type": "TextualBody",
     "purpose": "tagging",
     "value": "Object"
    }
   ],
   "target": {
    "id": "https://data.goldenagents.org/datasets/fricktalk2023/canvas/A16098000544",
    "selector": {
     "type": "FragmentSelector",
     "value": "xywh=838,2263,1764,156"
    }
   }
  },
  {
   "@context": "http://iiif.io/api/presentation/3/context.json",
   "id": "https://data.goldenagents.org/datasets/fricktalk2023/annotation/A16098000544/object26",
   "type": "Annotation",
   "motivation": "commenting",
   "body": [
    {
     "type": "TextualBody",
     "language": "nl",
     "value": "<p><b>Object detection</b><br><span>Original Label: </span>Een groot boeck<br>\n<span>Modernized Label: </span>een groot boek</p>"
    },
    {
     "type": "TextualBody",
     "purpose": "tagging",
     "value": "Object"
    }
   ],
   "target": {
    "id": "https://data.goldenagents.org/datasets/fricktalk2023/canvas/A16098000544",
    "selector": {
     "type": "FragmentSelector",
     "value": "xywh=838,2263,1764,156"
    }
   }
  },
  {
   "@context": "http://iiif.io/api/presentation/3/context.json",
   "id": "https://data.goldenagents.org/datasets/fricktalk2023/annotation/A16098000544/object27",
   "type": "Annotation",
   "motivation": "commenting",
   "body": [
    {
     "type": "TextualBody",
     "language": "nl",
     "value": "<p><b>Object detection</b><br><span>Original Label: </span>silver beslagh<br>\n<span>Modernized Label: </span>zilver beslag</p>"
    },
    {
     "type": "TextualBody",
     "purpose": "tagging",
     "value": "Object"
    }
   ],
   "target": {
    "id": "https://data.goldenagents.org/datasets/fricktalk2023/canvas/A16098000544",
    "selector": {
     "type": "FragmentSelector",
     "value": "xywh=317,2369,280,76"
    }
   }
  },
  {
   "@context": "http://iiif.io/api/presentation/3/context.json",
   "id": "https://data.goldenagents.org/datasets/fricktalk2023/annotation/A16098000544/object28",
   "type": "Annotation",
   "motivation": "commenting",
   "body": [
    {
     "type": "TextualBody",
     "language": "nl",
     "value": "<p><b>Object detection</b><br><span>Original Label: </span>Een achtkant silver taeffel<br>\n<span>Modernized Label: </span>een achtkant zilver tafel</p>"
    },
    {
     "type": "TextualBody",
     "purpose": "tagging",
     "value": "Object"
    }
   ],
   "target": {
    "id": "https://data.goldenagents.org/datasets/fricktalk2023/canvas/A16098000544",
    "selector": {
     "type": "FragmentSelector",
     "value": "xywh=279,2406,610,122"
    }
   }
  },
  {
   "@context": "http://iiif.io/api/presentation/3/context.json",
   "id": "https://data.goldenagents.org/datasets/fricktalk2023/annotation/A16098000544/object29",
   "type": "Annotation",
   "motivation": "commenting",
   "body": [
    {
     "type": "TextualBody",
     "language": "nl",
     "value": "<p><b>Object detection</b><br><span>Original Label: </span>Een sackje<br>\n<span>Modernized Label: </span>een zakje</p>"
    },
    {
     "type": "TextualBody",
     "purpose": "tagging",
     "value": "Object"
    }
   ],
   "target": {
    "id": "https://data.goldenagents.org/datasets/fricktalk2023/canvas/A16098000544",
    "selector": {
     "type": "FragmentSelector",
     "value": "xywh=298,2480,525,131"
    }
   }
  },
  {
   "@context": "http://iiif.io/api/presentation/3/context.json",
   "id": "https://data.goldenagents.org/datasets/fricktalk2023/annotation/A16098000544/object30",
   "type": "Annotation",
   "motivation": "commenting",
   "body": [
    {
     "type": "TextualBody",
     "language": "nl",
     "value": "<p><b>Object detection</b><br><span>Original Label: </span>Een sackje<br>\n<span>Modernized Label: </span>een zakje</p>"
    },
    {
     "type": "TextualBody",
     "purpose": "tagging",
     "value": "Object"
    }
   ],
   "target": {
    "id": "https://data.goldenagents.org/datasets/fricktalk2023/canvas/A16098000544",
    "selector": {
     "type": "FragmentSelector",
     "value": "xywh=319,2901,484,90"
    }
   }
  },
  {
   "@context": "http://iiif.io/api/presentation/3/context.json",
   "id": "https://data.goldenagents.org/datasets/fricktalk2023/annotation/A16098000544/object31",
   "type": "Annotation",
   "motivation": "commenting",
   "body": [
    {
     "type": "TextualBody",
     "language": "nl",
     "value": "<p><b>Object detection</b><br><span>Original Label: </span>silver beslag<br>\n<span>Modernized Label: </span>zilver beslag</p>"
    },
    {
     "type": "TextualBody",
     "purpose": "tagging",
     "value": "Object"
    }
   ],
   "target": {
    "id": "https://data.goldenagents.org/datasets/fricktalk2023/canvas/A16098000544",
    "selector": {
     "type": "FragmentSelector",
     "value": "xywh=335,2929,567,108"
    }
   }
  },
  {
   "@context": "http://iiif.io/api/presentation/3/context.json",
   "id": "https://data.goldenagents.org/datasets/fricktalk2023/annotation/A16098000544/object32",
   "type": "Annotation",
   "motivation": "commenting",
   "body": [
    {
     "type": "TextualBody",
     "language": "nl",
     "value": "<p><b>Object detection</b><br><span>Original Label: </span>Een doosje<br>\n<span>Modernized Label: </span>een doosje</p>"
    },
    {
     "type": "TextualBody",
     "purpose": "tagging",
     "value": "Object"
    }
   ],
   "target": {
    "id": "https://data.goldenagents.org/datasets/fricktalk2023/canvas/A16098000544",
    "selector": {
     "type": "FragmentSelector",
     "value": "xywh=336,2998,444,126"
    }
   }
  },
  {
   "@context": "http://iiif.io/api/presentation/3/context.json",
   "id": "https://data.goldenagents.org/datasets/fricktalk2023/annotation/A16098000544/object33",
   "type": "Annotation",
   "motivation": "commenting",
   "body": [
    {
     "type": "TextualBody",
     "language": "nl",
     "value": "<p><b>Object detection</b><br><span>Original Label: </span>Twee parldespelden<br>\n<span>Modernized Label: </span>twee parelspeld</p>"
    },
    {
     "type": "TextualBody",
     "purpose": "tagging",
     "value": "Object"
    }
   ],
   "target": {
    "id": "https://data.goldenagents.org/datasets/fricktalk2023/canvas/A16098000544",
    "selector": {
     "type": "FragmentSelector",
     "value": "xywh=313,3081,481,137"
    }
   }
  },
  {
   "@context": "http://iiif.io/api/presentation/3/context.json",
   "id": "https://data.goldenagents.org/datasets/fricktalk2023/annotation/A16098000544/object34",
   "type": "Annotation",
   "motivation": "commenting",
   "body": [
    {
     "type": "TextualBody",
     "language": "nl",
     "value": "<p><b>Object detection</b><br><span>Original Label: </span>packje net<br>\n<span>Modernized Label: </span>pakje netten</p>"
    },
    {
     "type": "TextualBody",
     "purpose": "tagging",
     "value": "Object"
    }
   ],
   "target": {
    "id": "https://data.goldenagents.org/datasets/fricktalk2023/canvas/A16098000544",
    "selector": {
     "type": "FragmentSelector",
     "value": "xywh=926,3178,1706,140"
    }
   }
  },
  {
   "@context": "http://iiif.io/api/presentation/3/context.json",
   "id": "https://data.goldenagents.org/datasets/fricktalk2023/annotation/A16098000544/object35",
   "type": "Annotation",
   "motivation": "commenting",
   "body": [
    {
     "type": "TextualBody",
     "language": "nl",
     "value": "<p><b>Object detection</b><br><span>Original Label: </span>Een silvere penningh<br>\n<span>Modernized Label: </span>een zilver penning</p>"
    },
    {
     "type": "TextualBody",
     "purpose": "tagging",
     "value": "Object"
    }
   ],
   "target": {
    "id": "https://data.goldenagents.org/datasets/fricktalk2023/canvas/A16098000544",
    "selector": {
     "type": "FragmentSelector",
     "value": "xywh=330,3255,501,111"
    }
   }
  },
  {
   "@context": "http://iiif.io/api/presentation/3/context.json",
   "id": "https://data.goldenagents.org/datasets/fricktalk2023/annotation/A16098000544/object36",
   "type": "Annotation",
   "motivation": "commenting",
   "body": [
    {
     "type": "TextualBody",
     "language": "nl",
     "value": "<p><b>Object detection</b><br><span>Original Label: </span>Ses stuckjens<br>\n<span>Modernized Label: </span>zes stukjes</p>"
    },
    {
     "type": "TextualBody",
     "purpose": "tagging",
     "value": "Object"
    }
   ],
   "target": {
    "id": "https://data.goldenagents.org/datasets/fricktalk2023/canvas/A16098000544",
    "selector": {
     "type": "FragmentSelector",
     "value": "xywh=294,3381,503,102"
    }
   }
  },
  {
   "@context": "http://iiif.io/api/presentation/3/context.json",
   "id": "https://data.goldenagents.org/datasets/fricktalk2023/annotation/A16098000544/object37",
   "type": "Annotation",
   "motivation": "commenting",
   "body": [
    {
     "type": "TextualBody",
     "language": "nl",
     "value": "<p><b>Object detection</b><br><span>Original Label: </span>gebroocken vorcken<br>\n<span>Modernized Label: </span>gebroken vork</p>"
    },
    {
     "type": "TextualBody",
     "purpose": "tagging",
     "value": "Object"
    }
   ],
   "target": {
    "id": "https://data.goldenagents.org/datasets/fricktalk2023/canvas/A16098000544",
    "selector": {
     "type": "FragmentSelector",
     "value": "xywh=344,3651,1352,163"
    }
   }
  },
  {
   "@context": "http://iiif.io/api/presentation/3/context.json",
   "id": "https://data.goldenagents.org/datasets/fricktalk2023/annotation/A16098000544/object38",
   "type": "Annotation",
   "motivation": "commenting",
   "body": [
    {
     "type": "TextualBody",
     "language": "nl",
     "value": "<p><b>Object detection</b><br><span>Original Label: </span>Een eijcke lissenaer<br>\n<span>Modernized Label: </span>een eiken lessenaar</p>"
    },
    {
     "type": "TextualBody",
     "purpose": "tagging",
     "value": "Object"
    }
   ],
   "target": {
    "id": "https://data.goldenagents.org/datasets/fricktalk2023/canvas/A16098000544",
    "selector": {
     "type": "FragmentSelector",
     "value": "xywh=3148,230,969,153"
    }
   }
  },
  {
   "@context": "http://iiif.io/api/presentation/3/context.json",
   "id": "https://data.goldenagents.org/datasets/fricktalk2023/annotation/A16098000544/object39",
   "type": "Annotation",
   "motivation": "commenting",
   "body": [
    {
     "type": "TextualBody",
     "language": "nl",
     "value": "<p><b>Object detection</b><br><span>Original Label: </span>gebroocken stuckjens<br>\n<span>Modernized Label: </span>gebroken stukjes</p>"
    },
    {
     "type": "TextualBody",
     "purpose": "tagging",
     "value": "Object"
    }
   ],
   "target": {
    "id": "https://data.goldenagents.org/datasets/fricktalk2023/canvas/A16098000544",
    "selector": {
     "type": "FragmentSelector",
     "value": "xywh=2856,333,2087,134"
    }
   }
  },
  {
   "@context": "http://iiif.io/api/presentation/3/context.json",
   "id": "https://data.goldenagents.org/datasets/fricktalk2023/annotation/A16098000544/object40",
   "type": "Annotation",
   "motivation": "commenting",
   "body": [
    {
     "type": "TextualBody",
     "language": "nl",
     "value": "<p><b>Object detection</b><br><span>Original Label: </span>een packxke<br>\n<span>Modernized Label: </span>een zakje</p>"
    },
    {
     "type": "TextualBody",
     "purpose": "tagging",
     "value": "Object"
    }
   ],
   "target": {
    "id": "https://data.goldenagents.org/datasets/fricktalk2023/canvas/A16098000544",
    "selector": {
     "type": "FragmentSelector",
     "value": "xywh=2823,415,2307,146"
    }
   }
  },
  {
   "@context": "http://iiif.io/api/presentation/3/context.json",
   "id": "https://data.goldenagents.org/datasets/fricktalk2023/annotation/A16098000544/object41",
   "type": "Annotation",
   "motivation": "commenting",
   "body": [
    {
     "type": "TextualBody",
     "language": "nl",
     "value": "<p><b>Object detection</b><br><span>Original Label: </span>Een silver beslagh<br>\n<span>Modernized Label: </span>een zilver beslag</p>"
    },
    {
     "type": "TextualBody",
     "purpose": "tagging",
     "value": "Object"
    }
   ],
   "target": {
    "id": "https://data.goldenagents.org/datasets/fricktalk2023/canvas/A16098000544",
    "selector": {
     "type": "FragmentSelector",
     "value": "xywh=2823,415,2307,146"
    }
   }
  },
  {
   "@context": "http://iiif.io/api/presentation/3/context.json",
   "id": "https://data.goldenagents.org/datasets/fricktalk2023/annotation/A16098000544/object42",
   "type": "Annotation",
   "motivation": "commenting",
   "body": [
    {
     "type": "TextualBody",
     "language": "nl",
     "value": "<p><b>Object detection</b><br><span>Original Label: </span>een boeck<br>\n<span>Modernized Label: </span>een boek</p>"
    },
    {
     "type": "TextualBody",
     "purpose": "tagging",
     "value": "Object"
    }
   ],
   "target": {
    "id": "https://data.goldenagents.org/datasets/fricktalk2023/canvas/A16098000544",
    "selector": {
     "type": "FragmentSelector",
     "value": "xywh=2855,539,275,63"
    }
   }
  },
  {
   "@context": "http://iiif.io/api/presentation/3/context.json",
   "id": "https://data.goldenagents.org/datasets/fricktalk2023/annotation/A16098000544/object43",
   "type": "Annotation",
   "motivation": "commenting",
   "body": [
    {
     "type": "TextualBody",
     "language": "nl",
     "value": "<p><b>Object detection</b><br><span>Original Label: </span>Een silver plaet<br>\n<span>Modernized Label: </span>een zilver plaat</p>"
    },
    {
     "type": "TextualBody",
     "purpose": "tagging",
     "value": "Object"
    }
   ],
   "target": {
    "id": "https://data.goldenagents.org/datasets/fricktalk2023/canvas/A16098000544",
    "selector": {
     "type": "FragmentSelector",
     "value": "xywh=2823,567,580,95"
    }
   }
  },
  {
   "@context": "http://iiif.io/api/presentation/3/context.json",
   "id": "https://data.goldenagents.org/datasets/fricktalk2023/annotation/A16098000544/object44",
   "type": "Annotation",
   "motivation": "commenting",
   "body": [
    {
     "type": "TextualBody",
     "language": "nl",
     "value": "<p><b>Object detection</b><br><span>Original Label: </span>kleijne parlkens<br>\n<span>Modernized Label: </span>kleine parel</p>"
    },
    {
     "type": "TextualBody",
     "purpose": "tagging",
     "value": "Object"
    }
   ],
   "target": {
    "id": "https://data.goldenagents.org/datasets/fricktalk2023/canvas/A16098000544",
    "selector": {
     "type": "FragmentSelector",
     "value": "xywh=2769,764,659,109"
    }
   }
  },
  {
   "@context": "http://iiif.io/api/presentation/3/context.json",
   "id": "https://data.goldenagents.org/datasets/fricktalk2023/annotation/A16098000544/object45",
   "type": "Annotation",
   "motivation": "commenting",
   "body": [
    {
     "type": "TextualBody",
     "language": "nl",
     "value": "<p><b>Object detection</b><br><span>Original Label: </span>Twee steentjens<br>\n<span>Modernized Label: </span>twee steentjes</p>"
    },
    {
     "type": "TextualBody",
     "purpose": "tagging",
     "value": "Object"
    }
   ],
   "target": {
    "id": "https://data.goldenagents.org/datasets/fricktalk2023/canvas/A16098000544",
    "selector": {
     "type": "FragmentSelector",
     "value": "xywh=2826,845,516,91"
    }
   }
  },
  {
   "@context": "http://iiif.io/api/presentation/3/context.json",
   "id": "https://data.goldenagents.org/datasets/fricktalk2023/annotation/A16098000544/object46",
   "type": "Annotation",
   "motivation": "commenting",
   "body": [
    {
     "type": "TextualBody",
     "language": "nl",
     "value": "<p><b>Object detection</b><br><span>Original Label: </span>een ringh<br>\n<span>Modernized Label: </span>een ring</p>"
    },
    {
     "type": "TextualBody",
     "purpose": "tagging",
     "value": "Object"
    }
   ],
   "target": {
    "id": "https://data.goldenagents.org/datasets/fricktalk2023/canvas/A16098000544",
    "selector": {
     "type": "FragmentSelector",
     "value": "xywh=2887,907,393,88"
    }
   }
  },
  {
   "@context": "http://iiif.io/api/presentation/3/context.json",
   "id": "https://data.goldenagents.org/datasets/fricktalk2023/annotation/A16098000544/object47",
   "type": "Annotation",
   "motivation": "commenting",
   "body": [
    {
     "type": "TextualBody",
     "language": "nl",
     "value": "<p><b>Object detection</b><br><span>Original Label: </span>Een grote fluwele Juweel<br>\n<span>Modernized Label: </span>een groot fluwelen juwelen</p>"
    },
    {
     "type": "TextualBody",
     "purpose": "tagging",
     "value": "Object"
    }
   ],
   "target": {
    "id": "https://data.goldenagents.org/datasets/fricktalk2023/canvas/A16098000544",
    "selector": {
     "type": "FragmentSelector",
     "value": "xywh=2711,948,613,107"
    }
   }
  },
  {
   "@context": "http://iiif.io/api/presentation/3/context.json",
   "id": "https://data.goldenagents.org/datasets/fricktalk2023/annotation/A16098000544/object48",
   "type": "Annotation",
   "motivation": "commenting",
   "body": [
    {
     "type": "TextualBody",
     "language": "nl",
     "value": "<p><b>Object detection</b><br><span>Original Label: </span>Een pacxke<br>\n<span>Modernized Label: </span>een zakje</p>"
    },
    {
     "type": "TextualBody",
     "purpose": "tagging",
     "value": "Object"
    }
   ],
   "target": {
    "id": "https://data.goldenagents.org/datasets/fricktalk2023/canvas/A16098000544",
    "selector": {
     "type": "FragmentSelector",
     "value": "xywh=3553,1100,1549,128"
    }
   }
  },
  {
   "@context": "http://iiif.io/api/presentation/3/context.json",
   "id": "https://data.goldenagents.org/datasets/fricktalk2023/annotation/A16098000544/object49",
   "type": "Annotation",
   "motivation": "commenting",
   "body": [
    {
     "type": "TextualBody",
     "language": "nl",
     "value": "<p><b>Object detection</b><br><span>Original Label: </span>Een gouwe lakense<br>\n<span>Modernized Label: </span>een gouden lakense</p>"
    },
    {
     "type": "TextualBody",
     "purpose": "tagging",
     "value": "Object"
    }
   ],
   "target": {
    "id": "https://data.goldenagents.org/datasets/fricktalk2023/canvas/A16098000544",
    "selector": {
     "type": "FragmentSelector",
     "value": "xywh=2805,1132,561,130"
    }
   }
  },
  {
   "@context": "http://iiif.io/api/presentation/3/context.json",
   "id": "https://data.goldenagents.org/datasets/fricktalk2023/annotation/A16098000544/object50",
   "type": "Annotation",
   "motivation": "commenting",
   "body": [
    {
     "type": "TextualBody",
     "language": "nl",
     "value": "<p><b>Object detection</b><br><span>Original Label: </span>en obligatien<br>\n<span>Modernized Label: </span>een obligatie</p>"
    },
    {
     "type": "TextualBody",
     "purpose": "tagging",
     "value": "Object"
    }
   ],
   "target": {
    "id": "https://data.goldenagents.org/datasets/fricktalk2023/canvas/A16098000544",
    "selector": {
     "type": "FragmentSelector",
     "value": "xywh=3539,1168,1612,178"
    }
   }
  },
  {
   "@context": "http://iiif.io/api/presentation/3/context.json",
   "id": "https://data.goldenagents.org/datasets/fricktalk2023/annotation/A16098000544/object51",
   "type": "Annotation",
   "motivation": "commenting",
   "body": [
    {
     "type": "TextualBody",
     "language": "nl",
     "value": "<p><b>Object detection</b><br><span>Original Label: </span>Een Psalmboecxke in<br>\n<span>Modernized Label: </span>een psalmboekje</p>"
    },
    {
     "type": "TextualBody",
     "purpose": "tagging",
     "value": "Object"
    }
   ],
   "target": {
    "id": "https://data.goldenagents.org/datasets/fricktalk2023/canvas/A16098000544",
    "selector": {
     "type": "FragmentSelector",
     "value": "xywh=2827,1291,469,146"
    }
   }
  },
  {
   "@context": "http://iiif.io/api/presentation/3/context.json",
   "id": "https://data.goldenagents.org/datasets/fricktalk2023/annotation/A16098000544/object52",
   "type": "Annotation",
   "motivation": "commenting",
   "body": [
    {
     "type": "TextualBody",
     "language": "nl",
     "value": "<p><b>Object detection</b><br><span>Original Label: </span>Een goude kettingh<br>\n<span>Modernized Label: </span>een gouden ketting</p>"
    },
    {
     "type": "TextualBody",
     "purpose": "tagging",
     "value": "Object"
    }
   ],
   "target": {
    "id": "https://data.goldenagents.org/datasets/fricktalk2023/canvas/A16098000544",
    "selector": {
     "type": "FragmentSelector",
     "value": "xywh=2830,1439,529,102"
    }
   }
  },
  {
   "@context": "http://iiif.io/api/presentation/3/context.json",
   "id": "https://data.goldenagents.org/datasets/fricktalk2023/annotation/A16098000544/object53",
   "type": "Annotation",
   "motivation": "commenting",
   "body": [
    {
     "type": "TextualBody",
     "language": "nl",
     "value": "<p><b>Object detection</b><br><span>Original Label: </span>een knoop<br>\n<span>Modernized Label: </span>een knoop</p>"
    },
    {
     "type": "TextualBody",
     "purpose": "tagging",
     "value": "Object"
    }
   ],
   "target": {
    "id": "https://data.goldenagents.org/datasets/fricktalk2023/canvas/A16098000544",
    "selector": {
     "type": "FragmentSelector",
     "value": "xywh=2861,1540,427,86"
    }
   }
  },
  {
   "@context": "http://iiif.io/api/presentation/3/context.json",
   "id": "https://data.goldenagents.org/datasets/fricktalk2023/annotation/A16098000544/object54",
   "type": "Annotation",
   "motivation": "commenting",
   "body": [
    {
     "type": "TextualBody",
     "language": "nl",
     "value": "<p><b>Object detection</b><br><span>Original Label: </span>en haecxken<br>\n<span>Modernized Label: </span>een haakje</p>"
    },
    {
     "type": "TextualBody",
     "purpose": "tagging",
     "value": "Object"
    }
   ],
   "target": {
    "id": "https://data.goldenagents.org/datasets/fricktalk2023/canvas/A16098000544",
    "selector": {
     "type": "FragmentSelector",
     "value": "xywh=2861,1540,427,86"
    }
   }
  },
  {
   "@context": "http://iiif.io/api/presentation/3/context.json",
   "id": "https://data.goldenagents.org/datasets/fricktalk2023/annotation/A16098000544/object55",
   "type": "Annotation",
   "motivation": "commenting",
   "body": [
    {
     "type": "TextualBody",
     "language": "nl",
     "value": "<p><b>Object detection</b><br><span>Original Label: </span>Westindische Compe<br>\n<span>Modernized Label: </span>Oostindische kom</p>"
    },
    {
     "type": "TextualBody",
     "purpose": "tagging",
     "value": "Object"
    }
   ],
   "target": {
    "id": "https://data.goldenagents.org/datasets/fricktalk2023/canvas/A16098000544",
    "selector": {
     "type": "FragmentSelector",
     "value": "xywh=3770,2630,1173,152"
    }
   }
  },
  {
   "@context": "http://iiif.io/api/presentation/3/context.json",
   "id": "https://data.goldenagents.org/datasets/fricktalk2023/annotation/A16098000544/object56",
   "type": "Annotation",
   "motivation": "commenting",
   "body": [
    {
     "type": "TextualBody",
     "language": "nl",
     "value": "<p><b>Object detection</b><br><span>Original Label: </span>oude obligatiepon<br>\n<span>Modernized Label: </span>oude obligatie</p>"
    },
    {
     "type": "TextualBody",
     "purpose": "tagging",
     "value": "Object"
    }
   ],
   "target": {
    "id": "https://data.goldenagents.org/datasets/fricktalk2023/canvas/A16098000544",
    "selector": {
     "type": "FragmentSelector",
     "value": "xywh=3772,2745,1265,140"
    }
   }
  },
  {
   "@context": "http://iiif.io/api/presentation/3/context.json",
   "id": "https://data.goldenagents.org/datasets/fricktalk2023/annotation/A16098000544/object57",
   "type": "Annotation",
   "motivation": "commenting",
   "body": [
    {
     "type": "TextualBody",
     "language": "nl",
     "value": "<p><b>Object detection</b><br><span>Original Label: </span>fijne diamante<br>\n<span>Modernized Label: </span>fijne diamanten</p>"
    },
    {
     "type": "TextualBody",
     "purpose": "tagging",
     "value": "Object"
    }
   ],
   "target": {
    "id": "https://data.goldenagents.org/datasets/fricktalk2023/canvas/A16098000544",
    "selector": {
     "type": "FragmentSelector",
     "value": "xywh=2879,3054,498,123"
    }
   }
  },
  {
   "@context": "http://iiif.io/api/presentation/3/context.json",
   "id": "https://data.goldenagents.org/datasets/fricktalk2023/annotation/A16098000544/object58",
   "type": "Annotation",
   "motivation": "commenting",
   "body": [
    {
     "type": "TextualBody",
     "language": "nl",
     "value": "<p><b>Object detection</b><br><span>Original Label: </span>Een tijne<br>\n<span>Modernized Label: </span>een tijntje</p>"
    },
    {
     "type": "TextualBody",
     "purpose": "tagging",
     "value": "Object"
    }
   ],
   "target": {
    "id": "https://data.goldenagents.org/datasets/fricktalk2023/canvas/A16098000544",
    "selector": {
     "type": "FragmentSelector",
     "value": "xywh=2876,3126,598,106"
    }
   }
  },
  {
   "@context": "http://iiif.io/api/presentation/3/context.json",
   "id": "https://data.goldenagents.org/datasets/fricktalk2023/annotation/A16098000544/object59",
   "type": "Annotation",
   "motivation": "commenting",
   "body": [
    {
     "type": "TextualBody",
     "language": "nl",
     "value": "<p><b>Object detection</b><br><span>Original Label: </span>Een obligatie<br>\n<span>Modernized Label: </span>een obligatie</p>"
    },
    {
     "type": "TextualBody",
     "purpose": "tagging",
     "value": "Object"
    }
   ],
   "target": {
    "id": "https://data.goldenagents.org/datasets/fricktalk2023/canvas/A16098000544",
    "selector": {
     "type": "FragmentSelector",
     "value": "xywh=3813,3129,1266,135"
    }
   }
  },
  {
   "@context": "http://iiif.io/api/presentation/3/context.json",
   "id": "https://data.goldenagents.org/datasets/fricktalk2023/annotation/A16098000544/object60",
   "type": "Annotation",
   "motivation": "commenting",
   "body": [
    {
     "type": "TextualBody",
     "language": "nl",
     "value": "<p><b>Object detection</b><br><span>Original Label: </span>fijne diamant<br>\n<span>Modernized Label: </span>fijne diamant</p>"
    },
    {
     "type": "TextualBody",
     "purpose": "tagging",
     "value": "Object"
    }
   ],
   "target": {
    "id": "https://data.goldenagents.org/datasets/fricktalk2023/canvas/A16098000544",
    "selector": {
     "type": "FragmentSelector",
     "value": "xywh=2902,3226,429,97"
    }
   }
  },
  {
   "@context": "http://iiif.io/api/presentation/3/context.json",
   "id": "https://data.goldenagents.org/datasets/fricktalk2023/annotation/A16098000544/object61",
   "type": "Annotation",
   "motivation": "commenting",
   "body": [
    {
     "type": "TextualBody",
     "language": "nl",
     "value": "<p><b>Object detection</b><br><span>Original Label: </span>Twee diamant Taeffelringe<br>\n<span>Modernized Label: </span>twee diamant tafel</p>"
    },
    {
     "type": "TextualBody",
     "purpose": "tagging",
     "value": "Object"
    }
   ],
   "target": {
    "id": "https://data.goldenagents.org/datasets/fricktalk2023/canvas/A16098000544",
    "selector": {
     "type": "FragmentSelector",
     "value": "xywh=2836,3329,720,115"
    }
   }
  },
  {
   "@context": "http://iiif.io/api/presentation/3/context.json",
   "id": "https://data.goldenagents.org/datasets/fricktalk2023/annotation/A16098000544/object62",
   "type": "Annotation",
   "motivation": "commenting",
   "body": [
    {
     "type": "TextualBody",
     "language": "nl",
     "value": "<p><b>Object detection</b><br><span>Original Label: </span>Een kleijn diamant ringetje<br>\n<span>Modernized Label: </span>een klein diamant ringetje</p>"
    },
    {
     "type": "TextualBody",
     "purpose": "tagging",
     "value": "Object"
    }
   ],
   "target": {
    "id": "https://data.goldenagents.org/datasets/fricktalk2023/canvas/A16098000544",
    "selector": {
     "type": "FragmentSelector",
     "value": "xywh=2854,3526,690,91"
    }
   }
  },
  {
   "@context": "http://iiif.io/api/presentation/3/context.json",
   "id": "https://data.goldenagents.org/datasets/fricktalk2023/annotation/A16098000544/object63",
   "type": "Annotation",
   "motivation": "commenting",
   "body": [
    {
     "type": "TextualBody",
     "language": "nl",
     "value": "<p><b>Object detection</b><br><span>Original Label: </span>goude knopen<br>\n<span>Modernized Label: </span>gouden knopen</p>"
    },
    {
     "type": "TextualBody",
     "purpose": "tagging",
     "value": "Object"
    }
   ],
   "target": {
    "id": "https://data.goldenagents.org/datasets/fricktalk2023/canvas/A16098000544",
    "selector": {
     "type": "FragmentSelector",
     "value": "xywh=2869,3586,731,96"
    }
   }
  },
  {
   "@context": "http://iiif.io/api/presentation/3/context.json",
   "id": "https://data.goldenagents.org/datasets/fricktalk2023/annotation/A16098000544/object64",
   "type": "Annotation",
   "motivation": "commenting",
   "body": [
    {
     "type": "TextualBody",
     "language": "nl",
     "value": "<p><b>Object detection</b><br><span>Original Label: </span>een Juweel koffertse<br>\n<span>Modernized Label: </span>een juwelenkoffertje</p>"
    },
    {
     "type": "TextualBody",
     "purpose": "tagging",
     "value": "Object"
    }
   ],
   "target": {
    "id": "https://data.goldenagents.org/datasets/fricktalk2023/canvas/A16098000544",
    "selector": {
     "type": "FragmentSelector",
     "value": "xywh=2857,3641,761,103"
    }
   }
  },
  {
   "@context": "http://iiif.io/api/presentation/3/context.json",
   "id": "https://data.goldenagents.org/datasets/fricktalk2023/annotation/A16098000544/object65",
   "type": "Annotation",
   "motivation": "commenting",
   "body": [
    {
     "type": "TextualBody",
     "language": "nl",
     "value": "<p><b>Object detection</b><br><span>Original Label: </span>Een laoctje<br>\n<span>Modernized Label: </span>een laken</p>"
    },
    {
     "type": "TextualBody",
     "purpose": "tagging",
     "value": "Object"
    }
   ],
   "target": {
    "id": "https://data.goldenagents.org/datasets/fricktalk2023/canvas/A16098000544",
    "selector": {
     "type": "FragmentSelector",
     "value": "xywh=3710,3684,1448,134"
    }
   }
  },
  {
   "@context": "http://iiif.io/api/presentation/3/context.json",
   "id": "https://data.goldenagents.org/datasets/fricktalk2023/annotation/A16098000544/object66",
   "type": "Annotation",
   "motivation": "commenting",
   "body": [
    {
     "type": "TextualBody",
     "language": "nl",
     "value": "<p><b>Object detection</b><br><span>Original Label: </span>gesteecken Neusdoeck<br>\n<span>Modernized Label: </span>gestoken neusdoek</p>"
    },
    {
     "type": "TextualBody",
     "purpose": "tagging",
     "value": "Object"
    }
   ],
   "target": {
    "id": "https://data.goldenagents.org/datasets/fricktalk2023/canvas/A16098000544",
    "selector": {
     "type": "FragmentSelector",
     "value": "xywh=2853,3701,829,116"
    }
   }
  }
 ]
}