{
 "@context": "http://iiif.io/api/presentation/3/context.json",
 "id": "iiif/annotations/A16098000427-objects.json",
 "type": "AnnotationPage",
 "items": [
  {
   "@context": "http://iiif.io/api/presentation/3/context.json",
   "id": "https://data.goldenagents.org/datasets/fricktalk2023/annotation/A16098000427/object1",
   "type": "Annotation",
   "motivation": "commenting",
   "body": [
    {
     "type": "TextualBody",
     "language": "nl",
     "value": "<p><b>Object detection</b><br><span>Original Label: </span>de loijers<br>\n<span>Modernized Label: </span>de luiers</p>"
    },
    {
     "type": "TextualBody",
     "purpose": "tagging",
     "value": "Object"
    }
   ],
   "target": {
    "id": "https://data.goldenagents.org/datasets/fricktalk2023/canvas/A16098000427",
    "selector": {
     "type": "FragmentSelector",
     "value": "xywh=873,534,1762,157"
    }
   }
  },
  {
   "@context": "http://iiif.io/api/presentation/3/context.json",
   "id": "https://data.goldenagents.org/datasets/fricktalk2023/annotation/A16098000427/object2",
   "type": "Annotation",
   "motivation": "commenting",
   "body": [
    {
     "type": "TextualBody",
     "language": "nl",
     "value": "<p><b>Object detection</b><br><span>Original Label: </span>resteent affier<br>\n<span>Modernized Label: </span>stenen safier</p>"
    },
    {
     "type": "TextualBody",
     "purpose": "tagging",
     "value": "Object"
    }
   ],
   "target": {
    "id": "https://data.goldenagents.org/datasets/fricktalk2023/canvas/A16098000427",
    "selector": {
     "type": "FragmentSelector",
     "value": "xywh=897,1377,1287,147"
    }
   }
  },
  {
   "@context": "http://iiif.io/api/presentation/3/context.json",
   "id": "https://data.goldenagents.org/datasets/fricktalk2023/annotation/A16098000427/object3",
   "type": "Annotation",
   "motivation": "commenting",
   "body": [
    {
     "type": "TextualBody",
     "language": "nl",
     "value": "<p><b>Object detection</b><br><span>Original Label: </span>de keijsers<br>\n<span>Modernized Label: </span>de ijzers</p>"
    },
    {
     "type": "TextualBody",
     "purpose": "tagging",
     "value": "Object"
    }
   ],
   "target": {
    "id": "https://data.goldenagents.org/datasets/fricktalk2023/canvas/A16098000427",
    "selector": {
     "type": "FragmentSelector",
     "value": "xywh=887,1676,1899,170"
    }
   }
  },
  {
   "@context": "http://iiif.io/api/presentation/3/context.json",
   "id": "https://data.goldenagents.org/datasets/fricktalk2023/annotation/A16098000427/object4",
   "type": "Annotation",
   "motivation": "commenting",
   "body": [
    {
     "type": "TextualBody",
     "language": "nl",
     "value": "<p><b>Object detection</b><br><span>Original Label: </span>tien pen<br>\n<span>Modernized Label: </span>tien pen</p>"
    },
    {
     "type": "TextualBody",
     "purpose": "tagging",
     "value": "Object"
    }
   ],
   "target": {
    "id": "https://data.goldenagents.org/datasets/fricktalk2023/canvas/A16098000427",
    "selector": {
     "type": "FragmentSelector",
     "value": "xywh=911,2399,1375,162"
    }
   }
  },
  {
   "@context": "http://iiif.io/api/presentation/3/context.json",
   "id": "https://data.goldenagents.org/datasets/fricktalk2023/annotation/A16098000427/object5",
   "type": "Annotation",
   "motivation": "commenting",
   "body": [
    {
     "type": "TextualBody",
     "language": "nl",
     "value": "<p><b>Object detection</b><br><span>Original Label: </span>Jdende Wnn<br>\n<span>Modernized Label: </span>zijden wijn</p>"
    },
    {
     "type": "TextualBody",
     "purpose": "tagging",
     "value": "Object"
    }
   ],
   "target": {
    "id": "https://data.goldenagents.org/datasets/fricktalk2023/canvas/A16098000427",
    "selector": {
     "type": "FragmentSelector",
     "value": "xywh=3362,1026,641,124"
    }
   }
  },
  {
   "@context": "http://iiif.io/api/presentation/3/context.json",
   "id": "https://data.goldenagents.org/datasets/fricktalk2023/annotation/A16098000427/object6",
   "type": "Annotation",
   "motivation": "commenting",
   "body": [
    {
     "type": "TextualBody",
     "language": "nl",
     "value": "<p><b>Object detection</b><br><span>Original Label: </span>de lostere<br>\n<span>Modernized Label: </span>de rooster</p>"
    },
    {
     "type": "TextualBody",
     "purpose": "tagging",
     "value": "Object"
    }
   ],
   "target": {
    "id": "https://data.goldenagents.org/datasets/fricktalk2023/canvas/A16098000427",
    "selector": {
     "type": "FragmentSelector",
     "value": "xywh=3264,1148,844,162"
    }
   }
  }
 ]
}